{"cameraMode":{"drawMode":0,"name":"Shaded","section":"Shading Mode"},"sceneLighting":true,"audioPlay":false,"sceneViewState":{"showFog":true,"showMaterialUpdate":false,"showSkybox":true,"showFlares":true,"showImageEffects":true,"showParticleSystems":true},"in2DMode":false,"pivot":{"x":23.04791259765625,"y":397.1749572753906,"z":189.17495727539063},"rotation":{"x":-0.081355519592762,"y":0.8996773362159729,"z":-0.1923120766878128,"w":-0.3839861750602722},"size":90.44430541992188,"orthographic":false}